ai_cli/__init__.py
ai_cli/_version.py
ai_cli/cli.py
ai_cli/config/__init__.py
ai_cli/config/manager.py
ai_cli/config/models.py
ai_cli/core/__init__.py
ai_cli/core/chat.py
ai_cli/core/history.py
ai_cli/core/messages.py
ai_cli/core/roles.py
ai_cli/providers/__init__.py
ai_cli/providers/base.py
ai_cli/providers/factory.py
ai_cli/providers/litellm_provider.py
ai_cli/ui/__init__.py
ai_cli/ui/interactive.py
ai_cli/ui/selector.py
ai_cli/ui/streaming.py
ai_cli/utils/__init__.py
ai_cli/utils/env.py
ai_cli/utils/text.py
ai_cli_chat-1.2.0.dist-info/METADATA
ai_cli_chat-1.2.0.dist-info/WHEEL
ai_cli_chat-1.2.0.dist-info/entry_points.txt
ai_cli_chat-1.2.0.dist-info/licenses/LICENSE
ai_cli_chat-1.2.0.dist-info/RECORD
