Metadata-Version: 2.4
Name: ai-cli-chat
Version: 1.2.0
Summary: Multi-model AI Chat at the CLI featuring round-table discussions
Project-URL: Homepage, https://github.com/YusiZhang/ai-cli
Project-URL: Repository, https://github.com/YusiZhang/ai-cli
Project-URL: Documentation, https://github.com/YusiZhang/ai-cli#readme
Project-URL: Issues, https://github.com/YusiZhang/ai-cli/issues
Project-URL: Changelog, https://github.com/YusiZhang/ai-cli/releases
Author-email: Yusi <5696168+YusiZhang@users.noreply.github.com>
Maintainer-email: Yusi <5696168+YusiZhang@users.noreply.github.com>
License: MIT
License-File: LICENSE
Keywords: ai,chat,chatgpt,cli,conversation,llm,roundtable
Classifier: Development Status :: 4 - Beta
Classifier: Intended Audience :: Developers
Classifier: Intended Audience :: End Users/Desktop
Classifier: License :: OSI Approved :: MIT License
Classifier: Operating System :: OS Independent
Classifier: Programming Language :: Python :: 3
Classifier: Programming Language :: Python :: 3.9
Classifier: Programming Language :: Python :: 3.10
Classifier: Programming Language :: Python :: 3.11
Classifier: Programming Language :: Python :: 3.12
Classifier: Topic :: Communications :: Chat
Classifier: Topic :: Scientific/Engineering :: Artificial Intelligence
Classifier: Topic :: Software Development :: Libraries :: Python Modules
Classifier: Topic :: Terminals
Classifier: Topic :: Utilities
Requires-Python: >=3.9
Requires-Dist: httpx>=0.25.0
Requires-Dist: litellm>=1.17.0
Requires-Dist: prompt-toolkit>=3.0.0
Requires-Dist: pydantic-settings>=2.1.0
Requires-Dist: pydantic>=2.5.0
Requires-Dist: pyperclip>=1.8.0
Requires-Dist: questionary>=2.0.0
Requires-Dist: rich>=13.7.0
Requires-Dist: toml>=0.10.0
Requires-Dist: typer>=0.9.0
Provides-Extra: dev
Requires-Dist: mypy>=1.0; extra == 'dev'
Requires-Dist: pre-commit>=3.0; extra == 'dev'
Requires-Dist: pytest-asyncio>=0.21; extra == 'dev'
Requires-Dist: pytest-cov>=4.0; extra == 'dev'
Requires-Dist: pytest-mock>=3.10; extra == 'dev'
Requires-Dist: pytest>=7.0; extra == 'dev'
Requires-Dist: ruff>=0.1.0; extra == 'dev'
Requires-Dist: twine>=4.0; extra == 'dev'
Provides-Extra: tui
Requires-Dist: textual>=0.44.0; extra == 'tui'
